{"is_source_file": true, "format": "JavaScript (React JSX)", "description": "This file is the main component for a React-based notes application. It manages state, handles data fetching from an API, offline fallback logic, and rendering of notes list and note form.", "external_files": ["./components/NotesList", "./components/NoteForm", "./components/OfflineBanner", "./api/client", "./storage/localFallback", "./App.css"], "external_methods": ["listNotes", "createNote", "deleteNote", "updateNote", "createFallbackNote", "deleteFallbackNote", "loadFallbackNotes", "replaceFallbackNotes", "updateFallbackNote"], "published": ["App"], "classes": [], "methods": [{"name": "normalizeNotes(list)", "description": "Normalizes raw note data into a consistent format.", "scope": "", "scopeKind": ""}, {"name": "sortNotes(notes)", "description": "Sorts notes, currently maintaining incoming order.", "scope": "", "scopeKind": ""}, {"name": "tryLoadFromServer()", "description": "Fetches notes from the server, updates state, handles offline fallback.", "scope": "App", "scopeKind": "function"}, {"name": "startAdd()", "description": "Prepares the UI to create a new note.", "scope": "App", "scopeKind": "function"}, {"name": "startEdit(note)", "description": "Prepares the UI to edit an existing note.", "scope": "App", "scopeKind": "function"}, {"name": "handleCreate(payload)", "description": "Handles creation of notes, with optimistic UI updates and offline fallback.", "scope": "App", "scopeKind": "function"}, {"name": "handleUpdate(payload)", "description": "Handles updating notes, with optimistic UI updates and offline fallback.", "scope": "App", "scopeKind": "function"}, {"name": "handleDelete(note)", "description": "Handles deletion of notes, with fallback logic.", "scope": "App", "scopeKind": "function"}, {"name": "App()", "scope": "", "scopeKind": "", "description": "unavailable"}], "calls": ["listNotes", "setNotes", "replaceFallbackNotes", "loadFallbackNotes", "createNote", "updateNote", "deleteNote", "createFallbackNote", "updateFallbackNote", "deleteFallbackNote"], "search-terms": ["NotesApp", "OfflineFallback", "note synchronization", "React notes component", "local fallback notes", "notes CRUD"], "state": 2, "file_id": 7, "knowledge_revision": 32, "git_revision": "6a03373e8413053089ed1d0c34a294410dd4bc55", "revision_history": [{"25": "520291f280d6af2689e752bec882ffb808771147"}, {"32": "6a03373e8413053089ed1d0c34a294410dd4bc55"}], "ctags": [{"_type": "tag", "name": "App", "path": "/home/kavia/workspace/code-generation/simple-notes-app-195053-195062/notes_frontend/src/App.js", "pattern": "/^function App() {$/", "language": "JavaScript", "kind": "function", "signature": "()"}, {"_type": "tag", "name": "content", "path": "/home/kavia/workspace/code-generation/simple-notes-app-195053-195062/notes_frontend/src/App.js", "pattern": "/^    const optimistic = { id: tempId, title: payload.title, content: payload.content ?? \"\" };$/", "language": "JavaScript", "kind": "property", "scope": "App.handleCreate.optimistic", "scopeKind": "class"}, {"_type": "tag", "name": "handleCreate", "path": "/home/kavia/workspace/code-generation/simple-notes-app-195053-195062/notes_frontend/src/App.js", "pattern": "/^  async function handleCreate(payload) {$/", "language": "JavaScript", "kind": "function", "signature": "(payload)", "scope": "App", "scopeKind": "function"}, {"_type": "tag", "name": "handleDelete", "path": "/home/kavia/workspace/code-generation/simple-notes-app-195053-195062/notes_frontend/src/App.js", "pattern": "/^  async function handleDelete(note) {$/", "language": "JavaScript", "kind": "function", "signature": "(note)", "scope": "App", "scopeKind": "function"}, {"_type": "tag", "name": "handleUpdate", "path": "/home/kavia/workspace/code-generation/simple-notes-app-195053-195062/notes_frontend/src/App.js", "pattern": "/^  async function handleUpdate(payload) {$/", "language": "JavaScript", "kind": "function", "signature": "(payload)", "scope": "App", "scopeKind": "function"}, {"_type": "tag", "name": "id", "path": "/home/kavia/workspace/code-generation/simple-notes-app-195053-195062/notes_frontend/src/App.js", "pattern": "/^    const optimistic = { id: tempId, title: payload.title, content: payload.content ?? \"\" };$/", "language": "JavaScript", "kind": "property", "scope": "App.handleCreate.optimistic", "scopeKind": "class"}, {"_type": "tag", "name": "loading", "path": "/home/kavia/workspace/code-generation/simple-notes-app-195053-195062/notes_frontend/src/App.js", "pattern": "/^              disabled={loading}$/", "language": "JavaScript", "kind": "field", "scope": "App.disabled", "scopeKind": "class"}, {"_type": "tag", "name": "mode", "path": "/home/kavia/workspace/code-generation/simple-notes-app-195053-195062/notes_frontend/src/App.js", "pattern": "/^            mode={mode}$/", "language": "JavaScript", "kind": "field", "scope": "App.mode", "scopeKind": "class"}, {"_type": "tag", "name": "mode", "path": "/home/kavia/workspace/code-generation/simple-notes-app-195053-195062/notes_frontend/src/App.js", "pattern": "/^            onSubmit={mode === \"edit\" ? handleUpdate : handleCreate}$/", "language": "JavaScript", "kind": "property", "scope": "App.onSubmit", "scopeKind": "class"}, {"_type": "tag", "name": "normalizeNotes", "path": "/home/kavia/workspace/code-generation/simple-notes-app-195053-195062/notes_frontend/src/App.js", "pattern": "/^function normalizeNotes(list) {$/", "language": "JavaScript", "kind": "function", "signature": "(list)"}, {"_type": "tag", "name": "onSubmit", "path": "/home/kavia/workspace/code-generation/simple-notes-app-195053-195062/notes_frontend/src/App.js", "pattern": "/^            onSubmit={mode === \"edit\" ? handleUpdate : handleCreate}$/", "language": "JavaScript", "kind": "class", "scope": "App", "scopeKind": "class"}, {"_type": "tag", "name": "optimistic", "path": "/home/kavia/workspace/code-generation/simple-notes-app-195053-195062/notes_frontend/src/App.js", "pattern": "/^    const optimistic = { id: tempId, title: payload.title, content: payload.content ?? \"\" };$/", "language": "JavaScript", "kind": "class", "scope": "App.handleCreate", "scopeKind": "class"}, {"_type": "tag", "name": "saving", "path": "/home/kavia/workspace/code-generation/simple-notes-app-195053-195062/notes_frontend/src/App.js", "pattern": "/^            isSaving={saving}$/", "language": "JavaScript", "kind": "field", "scope": "App.isSaving", "scopeKind": "class"}, {"_type": "tag", "name": "selected", "path": "/home/kavia/workspace/code-generation/simple-notes-app-195053-195062/notes_frontend/src/App.js", "pattern": "/^            initialNote={selected}$/", "language": "JavaScript", "kind": "field", "scope": "App.initialNote", "scopeKind": "class"}, {"_type": "tag", "name": "sortNotes", "path": "/home/kavia/workspace/code-generation/simple-notes-app-195053-195062/notes_frontend/src/App.js", "pattern": "/^function sortNotes(notes) {$/", "language": "JavaScript", "kind": "function", "signature": "(notes)"}, {"_type": "tag", "name": "startAdd", "path": "/home/kavia/workspace/code-generation/simple-notes-app-195053-195062/notes_frontend/src/App.js", "pattern": "/^            onCancel={startAdd}$/", "language": "JavaScript", "kind": "field", "scope": "App.onCancel", "scopeKind": "class"}, {"_type": "tag", "name": "startAdd", "path": "/home/kavia/workspace/code-generation/simple-notes-app-195053-195062/notes_frontend/src/App.js", "pattern": "/^  function startAdd() {$/", "language": "JavaScript", "kind": "function", "signature": "()", "scope": "App", "scopeKind": "function"}, {"_type": "tag", "name": "startEdit", "path": "/home/kavia/workspace/code-generation/simple-notes-app-195053-195062/notes_frontend/src/App.js", "pattern": "/^  function startEdit(note) {$/", "language": "JavaScript", "kind": "function", "signature": "(note)", "scope": "App", "scopeKind": "function"}, {"_type": "tag", "name": "title", "path": "/home/kavia/workspace/code-generation/simple-notes-app-195053-195062/notes_frontend/src/App.js", "pattern": "/^    const optimistic = { id: tempId, title: payload.title, content: payload.content ?? \"\" };$/", "language": "JavaScript", "kind": "property", "scope": "App.handleCreate.optimistic", "scopeKind": "class"}, {"_type": "tag", "name": "tryLoadFromServer", "path": "/home/kavia/workspace/code-generation/simple-notes-app-195053-195062/notes_frontend/src/App.js", "pattern": "/^              onClick={tryLoadFromServer}$/", "language": "JavaScript", "kind": "field", "scope": "App.onClick", "scopeKind": "class"}, {"_type": "tag", "name": "tryLoadFromServer", "path": "/home/kavia/workspace/code-generation/simple-notes-app-195053-195062/notes_frontend/src/App.js", "pattern": "/^  async function tryLoadFromServer() {$/", "language": "JavaScript", "kind": "function", "signature": "()", "scope": "App", "scopeKind": "function"}], "hash": "f0302d9eae29bcde4bc42e22ceb3f1d7", "format-version": 4, "code-base-name": "notes_frontend", "filename": "notes_frontend/src/App.js", "fields": [{"name": "const optimistic = { id: tempId, title: payload.title, content: payload.content ?? \"\" };", "scope": "App.handleCreate.optimistic", "scopeKind": "class", "description": "unavailable"}, {"name": "disabled={loading}", "scope": "App.disabled", "scopeKind": "class", "description": "unavailable"}, {"name": "mode={mode}", "scope": "App.mode", "scopeKind": "class", "description": "unavailable"}, {"name": "onSubmit={mode === \"edit\" ? handleUpdate : handleCreate}", "scope": "App.onSubmit", "scopeKind": "class", "description": "unavailable"}, {"name": "isSaving={saving}", "scope": "App.isSaving", "scopeKind": "class", "description": "unavailable"}, {"name": "initialNote={selected}", "scope": "App.initialNote", "scopeKind": "class", "description": "unavailable"}, {"name": "onCancel={startAdd}", "scope": "App.onCancel", "scopeKind": "class", "description": "unavailable"}, {"name": "onClick={tryLoadFromServer}", "scope": "App.onClick", "scopeKind": "class", "description": "unavailable"}]}